odoo/addons/sale_coupon_domain_product_discount_in_field/README.rst
odoo/addons/sale_coupon_domain_product_discount_in_field/__init__.py
odoo/addons/sale_coupon_domain_product_discount_in_field/__manifest__.py
odoo/addons/sale_coupon_domain_product_discount_in_field/i18n/it.po
odoo/addons/sale_coupon_domain_product_discount_in_field/i18n/sale_coupon_domain_product_discount_in_field.pot
odoo/addons/sale_coupon_domain_product_discount_in_field/models/__init__.py
odoo/addons/sale_coupon_domain_product_discount_in_field/models/sale_order.py
odoo/addons/sale_coupon_domain_product_discount_in_field/readme/CONTRIBUTORS.rst
odoo/addons/sale_coupon_domain_product_discount_in_field/readme/DESCRIPTION.rst
odoo/addons/sale_coupon_domain_product_discount_in_field/readme/USAGE.rst
odoo/addons/sale_coupon_domain_product_discount_in_field/static/description/icon.png
odoo/addons/sale_coupon_domain_product_discount_in_field/static/description/index.html
odoo/addons/sale_coupon_domain_product_discount_in_field/tests/__init__.py
odoo/addons/sale_coupon_domain_product_discount_in_field/tests/test_domain_product_discount_in_field.py
odoo14_addon_sale_coupon_domain_product_discount_in_field-14.0.1.0.2.dev1.dist-info/METADATA
odoo14_addon_sale_coupon_domain_product_discount_in_field-14.0.1.0.2.dev1.dist-info/WHEEL
odoo14_addon_sale_coupon_domain_product_discount_in_field-14.0.1.0.2.dev1.dist-info/top_level.txt
odoo14_addon_sale_coupon_domain_product_discount_in_field-14.0.1.0.2.dev1.dist-info/RECORD
